timeflake/__init__.py
timeflake/__main__.py
timeflake/flake.py
timeflake/utils.py
timeflake/extensions/__init__.py
timeflake/extensions/django/__init__.py
timeflake/extensions/peewee/__init__.py
timeflake-0.4.3.dist-info/LICENSE
timeflake-0.4.3.dist-info/METADATA
timeflake-0.4.3.dist-info/WHEEL
timeflake-0.4.3.dist-info/entry_points.txt
timeflake-0.4.3.dist-info/top_level.txt
timeflake-0.4.3.dist-info/RECORD
