Metadata-Version: 2.1
Name: timeflake
Version: 0.4.3
Summary: Timeflake is a 128-bit, roughly-ordered, URL-safe UUID. Inspired by Twitter's Snowflake, Instagram's ID and Firebase's PushID.
Home-page: https://github.com/anthonynsimon/timeflake
Author: Anthony Najjar Simon
License: MIT
Classifier: License :: OSI Approved :: MIT License
Classifier: Programming Language :: Python
Classifier: Programming Language :: Python :: 3.7
Classifier: Topic :: Software Development :: Libraries :: Python Modules
License-File: LICENSE
